importloc/__init__.py
importloc/exc.py
importloc/location.py
importloc/py.typed
importloc/testing.py
importloc/util.py
importloc-0.3.1.dist-info/METADATA
importloc-0.3.1.dist-info/WHEEL
importloc-0.3.1.dist-info/licenses/LICENSE
importloc-0.3.1.dist-info/RECORD
