Metadata-Version: 2.4
Name: importloc
Version: 0.3.1
Summary: Import Python objects from arbitrary locations specified by string
Project-URL: Documentation, https://importloc.readthedocs.io
Project-URL: Homepage, https://github.com/makukha/importloc
Project-URL: Repository, https://github.com/makukha/importloc
Project-URL: Issues, https://github.com/makukha/importloc/issues
Project-URL: Changelog, https://github.com/makukha/importloc/releases
License: MIT
License-File: LICENSE
Keywords: import,import-module,import-object,import-string,python
Classifier: Development Status :: 4 - Beta
Classifier: Environment :: Console
Classifier: Intended Audience :: Developers
Classifier: License :: OSI Approved :: MIT License
Classifier: Operating System :: OS Independent
Classifier: Programming Language :: Python
Classifier: Programming Language :: Python :: 3
Classifier: Programming Language :: Python :: 3.9
Classifier: Programming Language :: Python :: 3.10
Classifier: Programming Language :: Python :: 3.11
Classifier: Programming Language :: Python :: 3.12
Classifier: Programming Language :: Python :: 3.13
Classifier: Programming Language :: Python :: 3.14
Classifier: Programming Language :: Python :: Implementation :: CPython
Classifier: Topic :: Documentation
Classifier: Topic :: Software Development
Classifier: Topic :: Software Development :: Libraries
Classifier: Typing :: Typed
Requires-Python: >=3.9
Requires-Dist: typing-extensions>=4.12.2
